aws_sam_testing/__init__.py
aws_sam_testing/aws_resources.py
aws_sam_testing/aws_sam.py
aws_sam_testing/cfn.py
aws_sam_testing/cfn_tags.py
aws_sam_testing/core.py
aws_sam_testing/database.py
aws_sam_testing/localstack.py
aws_sam_testing/moto_server.py
aws_sam_testing/util.py
aws_sam_testing/pytest_addin/__init__.py
aws_sam_testing/pytest_addin/aws_context.py
aws_sam_testing/pytest_addin/aws_lambda_context.py
aws_sam_testing/pytest_addin/aws_localstack.py
aws_sam_testing/pytest_addin/aws_resources.py
aws_sam_testing/pytest_addin/aws_sam.py
aws_sam_testing/pytest_addin/database.py
aws_sam_testing-0.1.2.dist-info/METADATA
aws_sam_testing-0.1.2.dist-info/WHEEL
aws_sam_testing-0.1.2.dist-info/entry_points.txt
aws_sam_testing-0.1.2.dist-info/RECORD
