Metadata-Version: 2.4
Name: aws-sam-testing
Version: 0.1.2
Summary: Add your description here
Classifier: Framework :: Pytest
Requires-Python: >=3.13
Requires-Dist: aws-sam-cli>=1.139.0
Requires-Dist: aws-sam-translator>=1.97.0
Requires-Dist: flask-cors>=6.0.1
